src/__init__.py
src/evaluators.py
src/parser.py
3debt-0.0.6.dist-info/LICENSE
3debt-0.0.6.dist-info/METADATA
3debt-0.0.6.dist-info/WHEEL
3debt-0.0.6.dist-info/entry_points.txt
3debt-0.0.6.dist-info/top_level.txt
3debt-0.0.6.dist-info/RECORD
